[
  {
    "key": "SP_38_1",
    "type": "SP",
    "bookNumber": 38,
    "page": 1,
    "title_en": "There are laundry hanging on the clothes line in a neighbor's yard.",
    "title_kr": "이웃집 마당 빨래줄에 빨래가 널려 있어요.",
    "titleClip_en": "",
    "titleClip_kr": "",
    "sentances": [
      {
        "kr": "아기 돼지들이 소풍을 가요.",
        "priority": 3,
        "clip_kr": "",
        "value": "Piglets go on a picnic.",
        "clip": "",
        "key": null,
        "en": "Piglets go on a picnic.",
        "clip_en": "",
        "words": [
          "Piglets",
          "go",
          "on",
          "a",
          "picnic."
        ]
      },
      {
        "kr": "하양 돼지, 검정돼지, 하양 돼지, 검정 돼지.",
        "priority": 4,
        "clip_kr": "",
        "value": "White piglet, Black piglet, White piglet, Black piglet",
        "clip": "",
        "key": null,
        "en": "White piglet, Black piglet, White piglet, Black piglet",
        "clip_en": "",
        "words": [
          "White",
          "piglet,",
          "Black",
          "piglet,",
          "White",
          "piglet,",
          "Black",
          "piglet"
        ]
      },
      {
        "kr": "나란히 나란히 소풍을 가요.",
        "priority": 5,
        "clip_kr": "",
        "value": "They go on a picnic side by side.",
        "clip": "",
        "key": null,
        "en": "They go on a picnic side by side.",
        "clip_en": "",
        "words": [
          "They",
          "go",
          "on",
          "a",
          "picnic",
          "side",
          "by",
          "side."
        ]
      }
    ],
    "conversations": [
      {
        "priority": 3,
        "speaker": "A",
        "value": "Where were the piglets going?",
        "clip": ""
      },
      {
        "priority": 4,
        "speaker": "B",
        "value": "They were going on a picnic to the forest.",
        "clip": ""
      },
      {
        "priority": 5,
        "speaker": "A",
        "value": "How many piglets were there?",
        "clip": ""
      },
      {
        "priority": 6,
        "speaker": "B",
        "value": "There were four piglets.",
        "clip": ""
      }
    ],
    "words": [
      {
        "value": "black piglet",
        "extension": "jpg",
        "clip": ""
      },
      {
        "value": "kimbap",
        "extension": "jpg",
        "clip": ""
      },
      {
        "value": "pants",
        "extension": "jpg",
        "clip": ""
      },
      {
        "value": "rice balls",
        "extension": "jpg",
        "clip": ""
      },
      {
        "value": "snail",
        "extension": "jpg",
        "clip": ""
      },
      {
        "value": "t-shirt",
        "extension": "jpg",
        "clip": ""
      },
      {
        "value": "white piglet",
        "extension": "jpg",
        "clip": ""
      }
    ]
  },
  {
    "key": "SP_38_2",
    "type": "SP",
    "bookNumber": 38,
    "page": 2,
    "title_en": "Piglets go by a path through a forest.",
    "title_kr": "숲 속 오솔길을 지나가요.",
    "titleClip_en": "",
    "titleClip_kr": "",
    "sentances": [
      {
        "kr": "이웃집 마당 빨래줄에 빨래가 널려 있어요.",
        "priority": 7,
        "clip_kr": "",
        "value": "There are laundry hanging on the clothes line in a neighbor's yard.",
        "clip": "",
        "key": null,
        "en": "There are laundry hanging on the clothes line in a neighbor's yard.",
        "clip_en": "",
        "words": [
          "There",
          "are",
          "laundry",
          "hanging",
          "on",
          "the",
          "clothes",
          "line",
          "in",
          "a",
          "neighbor's",
          "yard."
        ]
      },
      {
        "kr": "바지, 티셔츠, 바지, 티셔츠,",
        "priority": 8,
        "clip_kr": "",
        "value": "Pants, T-shirt, Pants, T-shirt",
        "clip": "",
        "key": null,
        "en": "Pants, T-shirt, Pants, T-shirt",
        "clip_en": "",
        "words": [
          "Pants,",
          "T-shirt,",
          "Pants,",
          "T-shirt"
        ]
      },
      {
        "kr": "나란히 나란히 널려 있어요.",
        "priority": 9,
        "clip_kr": "",
        "value": "They are hanging side by side.",
        "clip": "",
        "key": null,
        "en": "They are hanging side by side.",
        "clip_en": "",
        "words": [
          "They",
          "are",
          "hanging",
          "side",
          "by",
          "side."
        ]
      }
    ],
    "conversations": [
      {
        "priority": 7,
        "speaker": "A",
        "value": "What did they see in a neighbor's yard?",
        "clip": ""
      },
      {
        "priority": 8,
        "speaker": "B",
        "value": "They saw the laundry hanging on the clothes.",
        "clip": ""
      },
      {
        "priority": 9,
        "speaker": "A",
        "value": "What kinds of laundry hanging?",
        "clip": ""
      },
      {
        "priority": 10,
        "speaker": "B",
        "value": "There were pants and T-shirt.",
        "clip": ""
      }
    ],
    "words": [
      {
        "value": "black piglet",
        "extension": "jpg",
        "clip": ""
      },
      {
        "value": "kimbap",
        "extension": "jpg",
        "clip": ""
      },
      {
        "value": "pants",
        "extension": "jpg",
        "clip": ""
      },
      {
        "value": "rice balls",
        "extension": "jpg",
        "clip": ""
      },
      {
        "value": "snail",
        "extension": "jpg",
        "clip": ""
      },
      {
        "value": "t-shirt",
        "extension": "jpg",
        "clip": ""
      },
      {
        "value": "white piglet",
        "extension": "jpg",
        "clip": ""
      }
    ]
  },
  {
    "key": "SP_38_3",
    "type": "SP",
    "bookNumber": 38,
    "page": 3,
    "title_en": "The lotuses bloom on a pond.",
    "title_kr": "연못에 연꽃이 피어 있어요.",
    "titleClip_en": "",
    "titleClip_kr": "",
    "sentances": [
      {
        "kr": "숲 속 오솔길을 지나가요.",
        "priority": 11,
        "clip_kr": "",
        "value": "Piglets go by a path through a forest.",
        "clip": "",
        "key": null,
        "en": "Piglets go by a path through a forest.",
        "clip_en": "",
        "words": [
          "Piglets",
          "go",
          "by",
          "a",
          "path",
          "through",
          "a",
          "forest."
        ]
      },
      {
        "kr": "작은 나무, 큰 나무, 작은 나무, 큰 나무.",
        "priority": 12,
        "clip_kr": "",
        "value": "Small tree, Big tree, Small tree, Big tree",
        "clip": "",
        "key": null,
        "en": "Small tree, Big tree, Small tree, Big tree",
        "clip_en": "",
        "words": [
          "Small",
          "tree,",
          "Big",
          "tree,",
          "Small",
          "tree,",
          "Big",
          "tree"
        ]
      },
      {
        "kr": "나란히 나란히 서 있어요.",
        "priority": 13,
        "clip_kr": "",
        "value": "They are standing side by side.",
        "clip": "",
        "key": null,
        "en": "They are standing side by side.",
        "clip_en": "",
        "words": [
          "They",
          "are",
          "standing",
          "side",
          "by",
          "side."
        ]
      }
    ],
    "conversations": [
      {
        "priority": 11,
        "speaker": "A",
        "value": "What did they see on a path through a forest?",
        "clip": ""
      },
      {
        "priority": 12,
        "speaker": "B",
        "value": "They saw some trees on the path.",
        "clip": ""
      },
      {
        "priority": 13,
        "speaker": "A",
        "value": "What trees did they see?",
        "clip": ""
      },
      {
        "priority": 14,
        "speaker": "B",
        "value": "They saw that the four trees were standing side by side.",
        "clip": ""
      }
    ],
    "words": [
      {
        "value": "black piglet",
        "extension": "jpg",
        "clip": ""
      },
      {
        "value": "kimbap",
        "extension": "jpg",
        "clip": ""
      },
      {
        "value": "pants",
        "extension": "jpg",
        "clip": ""
      },
      {
        "value": "rice balls",
        "extension": "jpg",
        "clip": ""
      },
      {
        "value": "snail",
        "extension": "jpg",
        "clip": ""
      },
      {
        "value": "t-shirt",
        "extension": "jpg",
        "clip": ""
      },
      {
        "value": "white piglet",
        "extension": "jpg",
        "clip": ""
      }
    ]
  },
  {
    "key": "SP_38_4",
    "type": "SP",
    "bookNumber": 38,
    "page": 4,
    "title_en": "Snail family go on a picnic, too.",
    "title_kr": "달팽이 가족도 소풍을 가요.",
    "titleClip_en": "",
    "titleClip_kr": "",
    "sentances": [
      {
        "kr": "연못에 연꽃이 피어 있어요.",
        "priority": 15,
        "clip_kr": "",
        "value": "The lotuses bloom on a pond.",
        "clip": "",
        "key": null,
        "en": "The lotuses bloom on a pond.",
        "clip_en": "",
        "words": [
          "The",
          "lotuses",
          "bloom",
          "on",
          "a",
          "pond."
        ]
      },
      {
        "kr": "하얀 연꽃, 분홍 연꽃, 하양 연꽃, 분홍 연꽃.",
        "priority": 16,
        "clip_kr": "",
        "value": "White lotus, Pink lotus, White lotus, Pink lotus",
        "clip": "",
        "key": null,
        "en": "White lotus, Pink lotus, White lotus, Pink lotus",
        "clip_en": "",
        "words": [
          "White",
          "lotus,",
          "Pink",
          "lotus,",
          "White",
          "lotus,",
          "Pink",
          "lotus"
        ]
      },
      {
        "kr": "나란히 나란히 피어 있어요.",
        "priority": 17,
        "clip_kr": "",
        "value": "They are blooming side by side.",
        "clip": "",
        "key": null,
        "en": "They are blooming side by side.",
        "clip_en": "",
        "words": [
          "They",
          "are",
          "blooming",
          "side",
          "by",
          "side."
        ]
      }
    ],
    "conversations": [
      {
        "priority": 15,
        "speaker": "A",
        "value": "What were there on a pond?",
        "clip": ""
      },
      {
        "priority": 16,
        "speaker": "B",
        "value": "There were lotuses flatting on pond.",
        "clip": ""
      },
      {
        "priority": 17,
        "speaker": "A",
        "value": "What color were they?",
        "clip": ""
      },
      {
        "priority": 18,
        "speaker": "B",
        "value": "They were white and pink.",
        "clip": ""
      }
    ],
    "words": [
      {
        "value": "black piglet",
        "extension": "jpg",
        "clip": ""
      },
      {
        "value": "kimbap",
        "extension": "jpg",
        "clip": ""
      },
      {
        "value": "pants",
        "extension": "jpg",
        "clip": ""
      },
      {
        "value": "rice balls",
        "extension": "jpg",
        "clip": ""
      },
      {
        "value": "snail",
        "extension": "jpg",
        "clip": ""
      },
      {
        "value": "t-shirt",
        "extension": "jpg",
        "clip": ""
      },
      {
        "value": "white piglet",
        "extension": "jpg",
        "clip": ""
      }
    ]
  },
  {
    "key": "SP_38_5",
    "type": "SP",
    "bookNumber": 38,
    "page": 5,
    "title_en": "Piglets have a lunch at the park.",
    "title_kr": "공원에서 도시락을 먹어요.",
    "titleClip_en": "",
    "titleClip_kr": "",
    "sentances": [
      {
        "kr": "달팽이 가족도 소풍을 가요.",
        "priority": 19,
        "clip_kr": "",
        "value": "Snail family go on a picnic, too.",
        "clip": "",
        "key": null,
        "en": "Snail family go on a picnic, too.",
        "clip_en": "",
        "words": [
          "Snail",
          "family",
          "go",
          "on",
          "a",
          "picnic,",
          "too."
        ]
      },
      {
        "kr": "작은 달팽이, 큰 달팽이, 작은 달팽이, 큰 달팽이.",
        "priority": 20,
        "clip_kr": "",
        "value": "Small snail, Big snail, Small snail, Big snail",
        "clip": "",
        "key": null,
        "en": "Small snail, Big snail, Small snail, Big snail",
        "clip_en": "",
        "words": [
          "Small",
          "snail,",
          "Big",
          "snail,",
          "Small",
          "snail,",
          "Big",
          "snail"
        ]
      },
      {
        "kr": "나란히 나란히 기어가요.",
        "priority": 21,
        "clip_kr": "",
        "value": "They are crawling side by side.",
        "clip": "",
        "key": null,
        "en": "They are crawling side by side.",
        "clip_en": "",
        "words": [
          "They",
          "are",
          "crawling",
          "side",
          "by",
          "side."
        ]
      }
    ],
    "conversations": [
      {
        "priority": 19,
        "speaker": "A",
        "value": "What did they see on a grass?",
        "clip": ""
      },
      {
        "priority": 20,
        "speaker": "B",
        "value": "They saw snail family on a grass.",
        "clip": ""
      },
      {
        "priority": 21,
        "speaker": "A",
        "value": "What did snail family do?",
        "clip": ""
      },
      {
        "priority": 22,
        "speaker": "B",
        "value": "Oh, they were going on a picnic like the piglets.",
        "clip": ""
      }
    ],
    "words": [
      {
        "value": "black piglet",
        "extension": "jpg",
        "clip": ""
      },
      {
        "value": "kimbap",
        "extension": "jpg",
        "clip": ""
      },
      {
        "value": "pants",
        "extension": "jpg",
        "clip": ""
      },
      {
        "value": "rice balls",
        "extension": "jpg",
        "clip": ""
      },
      {
        "value": "snail",
        "extension": "jpg",
        "clip": ""
      },
      {
        "value": "t-shirt",
        "extension": "jpg",
        "clip": ""
      },
      {
        "value": "white piglet",
        "extension": "jpg",
        "clip": ""
      }
    ]
  },
  {
    "key": "SP_38_6",
    "type": "SP",
    "bookNumber": 38,
    "page": 6,
    "title_en": "Piglets are sleepy.",
    "title_kr": "아기 돼지들은 슬슬 졸음이 와요.",
    "titleClip_en": "",
    "titleClip_kr": "",
    "sentances": [
      {
        "kr": "공원에서 도시락을 먹어요.",
        "priority": 23,
        "clip_kr": "",
        "value": "Piglets have a lunch at the park.",
        "clip": "",
        "key": null,
        "en": "Piglets have a lunch at the park.",
        "clip_en": "",
        "words": [
          "Piglets",
          "have",
          "a",
          "lunch",
          "at",
          "the",
          "park."
        ]
      },
      {
        "kr": "주먹밥, 김밥, 주먹밥, 김밥",
        "priority": 24,
        "clip_kr": "",
        "value": "Rice ball, Kim bob, Rice ball, Kim bob,",
        "clip": "",
        "key": null,
        "en": "Rice ball, Kim bob, Rice ball, Kim bob,",
        "clip_en": "",
        "words": [
          "Rice",
          "ball,",
          "Kim",
          "bob,",
          "Rice",
          "ball,",
          "Kim",
          "bob,"
        ]
      },
      {
        "kr": "모두모두 맛있어요.",
        "priority": 25,
        "clip_kr": "",
        "value": "They are all delicious.",
        "clip": "",
        "key": null,
        "en": "They are all delicious.",
        "clip_en": "",
        "words": [
          "They",
          "are",
          "all",
          "delicious."
        ]
      }
    ],
    "conversations": [
      {
        "priority": 23,
        "speaker": "A",
        "value": "What did the piglets do at the park?",
        "clip": ""
      },
      {
        "priority": 24,
        "speaker": "B",
        "value": "They had a lunch together.",
        "clip": ""
      },
      {
        "priority": 25,
        "speaker": "A",
        "value": "What kinds of food did they have for a lunch?",
        "clip": ""
      },
      {
        "priority": 26,
        "speaker": "B",
        "value": "They had rice ball and kimbab for a lunch.",
        "clip": ""
      }
    ],
    "words": [
      {
        "value": "black piglet",
        "extension": "jpg",
        "clip": ""
      },
      {
        "value": "kimbap",
        "extension": "jpg",
        "clip": ""
      },
      {
        "value": "pants",
        "extension": "jpg",
        "clip": ""
      },
      {
        "value": "rice balls",
        "extension": "jpg",
        "clip": ""
      },
      {
        "value": "snail",
        "extension": "jpg",
        "clip": ""
      },
      {
        "value": "t-shirt",
        "extension": "jpg",
        "clip": ""
      },
      {
        "value": "white piglet",
        "extension": "jpg",
        "clip": ""
      }
    ]
  },
  {
    "key": "SP_38_7",
    "type": "SP",
    "bookNumber": 38,
    "page": 7,
    "title_en": "They are lying and taking a nap side by side.",
    "title_kr": "나란히 나란히 낮잠을 자요.",
    "titleClip_en": "",
    "titleClip_kr": "",
    "sentances": [
      {
        "kr": "아기 돼지들은 슬슬 졸음이 와요.",
        "priority": 27,
        "clip_kr": "",
        "value": "Piglets are sleepy.",
        "clip": "",
        "key": null,
        "en": "Piglets are sleepy.",
        "clip_en": "",
        "words": [
          "Piglets",
          "are",
          "sleepy."
        ]
      },
      {
        "kr": "하양 돼지, 검정돼지, 하양 돼지, 검정 돼지.",
        "priority": 28,
        "clip_kr": "",
        "value": "White piglet, Black piglet, White piglet, Black piglet",
        "clip": "",
        "key": null,
        "en": "White piglet, Black piglet, White piglet, Black piglet",
        "clip_en": "",
        "words": [
          "White",
          "piglet,",
          "Black",
          "piglet,",
          "White",
          "piglet,",
          "Black",
          "piglet"
        ]
      },
      {
        "kr": "나란히 나란히 낮잠을 자요.",
        "priority": 29,
        "clip_kr": "",
        "value": "They are lying and taking a nap side by side.",
        "clip": "",
        "key": null,
        "en": "They are lying and taking a nap side by side.",
        "clip_en": "",
        "words": [
          "They",
          "are",
          "lying",
          "and",
          "taking",
          "a",
          "nap",
          "side",
          "by",
          "side."
        ]
      }
    ],
    "conversations": [
      {
        "priority": 27,
        "speaker": "A",
        "value": "What did they do after eating lunch?",
        "clip": ""
      },
      {
        "priority": 28,
        "speaker": "B",
        "value": "They were lying on the ground and taking a nap.",
        "clip": ""
      },
      {
        "priority": 29,
        "speaker": "A",
        "value": "Wow. They had really good time at the forest!",
        "clip": ""
      }
    ],
    "words": [
      {
        "value": "black piglet",
        "extension": "jpg",
        "clip": ""
      },
      {
        "value": "kimbap",
        "extension": "jpg",
        "clip": ""
      },
      {
        "value": "pants",
        "extension": "jpg",
        "clip": ""
      },
      {
        "value": "rice balls",
        "extension": "jpg",
        "clip": ""
      },
      {
        "value": "snail",
        "extension": "jpg",
        "clip": ""
      },
      {
        "value": "t-shirt",
        "extension": "jpg",
        "clip": ""
      },
      {
        "value": "white piglet",
        "extension": "jpg",
        "clip": ""
      }
    ]
  }
]