[
  {
    "key": "SP_7_1",
    "type": "SP",
    "bookNumber": 7,
    "page": 1,
    "title_en": "There are two round fish!",
    "title_kr": "둥글둥글 물고기가 두 마리 있어요!",
    "titleClip_en": "",
    "titleClip_kr": "",
    "sentances": [
      {
        "kr": "둥글둥글 물고기가 몇마리 일까?",
        "priority": 3,
        "clip_kr": "",
        "value": "How many round fish are there?",
        "clip": "",
        "key": null,
        "en": "How many round fish are there?",
        "clip_en": "",
        "words": [
          "How",
          "many",
          "round",
          "fish",
          "are",
          "there?"
        ]
      },
      {
        "kr": "1+1 = 2",
        "priority": 4,
        "clip_kr": "",
        "value": "1 + 1 = 2",
        "clip": "",
        "key": null,
        "en": "1 + 1 = 2",
        "clip_en": "",
        "words": [
          "1",
          "+",
          "1",
          "=",
          "2"
        ]
      },
      {
        "kr": "",
        "priority": 5,
        "clip_kr": "",
        "value": "One and one is two.",
        "clip": "",
        "key": null,
        "en": "One and one is two.",
        "clip_en": "",
        "words": [
          "One",
          "and",
          "one",
          "is",
          "two."
        ]
      }
    ],
    "conversations": [
      {
        "priority": 3,
        "speaker": "A",
        "value": "Are you good at math?",
        "clip": ""
      },
      {
        "priority": 4,
        "speaker": "B",
        "value": "No, I am not.",
        "clip": ""
      },
      {
        "priority": 5,
        "speaker": "B",
        "value": "Math is really hard.",
        "clip": ""
      },
      {
        "priority": 6,
        "speaker": "A",
        "value": "I'll help you solve the math problems.",
        "clip": ""
      }
    ],
    "words": [
      {
        "value": "crab",
        "extension": "jpg",
        "clip": ""
      },
      {
        "value": "lobsterclam",
        "extension": "jpg",
        "clip": ""
      },
      {
        "value": "octopus",
        "extension": "jpg",
        "clip": ""
      },
      {
        "value": "round fish",
        "extension": "jpg",
        "clip": ""
      },
      {
        "value": "sharp fish",
        "extension": "jpg",
        "clip": ""
      },
      {
        "value": "starfish",
        "extension": "jpg",
        "clip": ""
      }
    ]
  },
  {
    "key": "SP_7_2",
    "type": "SP",
    "bookNumber": 7,
    "page": 2,
    "title_en": "How many sharp fish are there?",
    "title_kr": "뾰족뽀족 물고기가 몇마리 일까?",
    "titleClip_en": "",
    "titleClip_kr": "",
    "sentances": [
      {
        "kr": "둥글둥글 물고기가 두 마리 있어요!",
        "priority": 7,
        "clip_kr": "",
        "value": "There are two round fish!",
        "clip": "",
        "key": null,
        "en": "There are two round fish!",
        "clip_en": "",
        "words": [
          "There",
          "are",
          "two",
          "round",
          "fish!"
        ]
      }
    ],
    "conversations": [
      {
        "priority": 7,
        "speaker": "B",
        "value": "Thank you!",
        "clip": ""
      },
      {
        "priority": 8,
        "speaker": "B",
        "value": "There is one red fish.",
        "clip": ""
      },
      {
        "priority": 9,
        "speaker": "A",
        "value": "And, there is one purple fish.",
        "clip": ""
      },
      {
        "priority": 10,
        "speaker": "A",
        "value": "Then, how many fish are there?",
        "clip": ""
      },
      {
        "priority": 11,
        "speaker": "B",
        "value": "I got it!",
        "clip": ""
      },
      {
        "priority": 12,
        "speaker": "B",
        "value": "There are two fish!",
        "clip": ""
      },
      {
        "priority": 13,
        "speaker": "A",
        "value": "Good job!",
        "clip": ""
      }
    ],
    "words": [
      {
        "value": "crab",
        "extension": "jpg",
        "clip": ""
      },
      {
        "value": "lobsterclam",
        "extension": "jpg",
        "clip": ""
      },
      {
        "value": "octopus",
        "extension": "jpg",
        "clip": ""
      },
      {
        "value": "round fish",
        "extension": "jpg",
        "clip": ""
      },
      {
        "value": "sharp fish",
        "extension": "jpg",
        "clip": ""
      },
      {
        "value": "starfish",
        "extension": "jpg",
        "clip": ""
      }
    ]
  },
  {
    "key": "SP_7_3",
    "type": "SP",
    "bookNumber": 7,
    "page": 3,
    "title_en": "There are two sharp fish!",
    "title_kr": "뾰족뽀족 물고기가 두 마리 있어요!",
    "titleClip_en": "",
    "titleClip_kr": "",
    "sentances": [
      {
        "kr": "뾰족뽀족 물고기가 몇마리 일까?",
        "priority": 14,
        "clip_kr": "",
        "value": "How many sharp fish are there?",
        "clip": "",
        "key": null,
        "en": "How many sharp fish are there?",
        "clip_en": "",
        "words": [
          "How",
          "many",
          "sharp",
          "fish",
          "are",
          "there?"
        ]
      },
      {
        "kr": "4-2 = 2",
        "priority": 15,
        "clip_kr": "",
        "value": "4 - 2 = 2",
        "clip": "",
        "key": null,
        "en": "4 - 2 = 2",
        "clip_en": "",
        "words": [
          "4",
          "-",
          "2",
          "=",
          "2"
        ]
      },
      {
        "kr": "",
        "priority": 16,
        "clip_kr": "",
        "value": "Four minus two equals two.",
        "clip": "",
        "key": null,
        "en": "Four minus two equals two.",
        "clip_en": "",
        "words": [
          "Four",
          "minus",
          "two",
          "equals",
          "two."
        ]
      }
    ],
    "conversations": [
      {
        "priority": 14,
        "speaker": "A",
        "value": "There are four sharp fish.",
        "clip": ""
      },
      {
        "priority": 15,
        "speaker": "B",
        "value": "Oh! Shark eats sharp fish.",
        "clip": ""
      },
      {
        "priority": 16,
        "speaker": "A",
        "value": "Then, four sharp fish minus two sharp fish equals…",
        "clip": ""
      },
      {
        "priority": 17,
        "speaker": "B",
        "value": "Well.. there are two fish.",
        "clip": ""
      }
    ],
    "words": [
      {
        "value": "crab",
        "extension": "jpg",
        "clip": ""
      },
      {
        "value": "lobsterclam",
        "extension": "jpg",
        "clip": ""
      },
      {
        "value": "octopus",
        "extension": "jpg",
        "clip": ""
      },
      {
        "value": "round fish",
        "extension": "jpg",
        "clip": ""
      },
      {
        "value": "sharp fish",
        "extension": "jpg",
        "clip": ""
      },
      {
        "value": "starfish",
        "extension": "jpg",
        "clip": ""
      }
    ]
  },
  {
    "key": "SP_7_4",
    "type": "SP",
    "bookNumber": 7,
    "page": 4,
    "title_en": "How many limply octopuses are there?",
    "title_kr": "흐느적흐느적 문어가 몇마리 일까?",
    "titleClip_en": "",
    "titleClip_kr": "",
    "sentances": [
      {
        "kr": "뾰족뽀족 물고기가 두 마리 있어요!",
        "priority": 18,
        "clip_kr": "",
        "value": "There are two sharp fish!",
        "clip": "",
        "key": null,
        "en": "There are two sharp fish!",
        "clip_en": "",
        "words": [
          "There",
          "are",
          "two",
          "sharp",
          "fish!"
        ]
      }
    ],
    "conversations": [
      {
        "priority": 18,
        "speaker": "B",
        "value": "So, four minus two equals two!",
        "clip": ""
      },
      {
        "priority": 19,
        "speaker": "A",
        "value": "Great job!",
        "clip": ""
      }
    ],
    "words": [
      {
        "value": "crab",
        "extension": "jpg",
        "clip": ""
      },
      {
        "value": "lobsterclam",
        "extension": "jpg",
        "clip": ""
      },
      {
        "value": "octopus",
        "extension": "jpg",
        "clip": ""
      },
      {
        "value": "round fish",
        "extension": "jpg",
        "clip": ""
      },
      {
        "value": "sharp fish",
        "extension": "jpg",
        "clip": ""
      },
      {
        "value": "starfish",
        "extension": "jpg",
        "clip": ""
      }
    ]
  },
  {
    "key": "SP_7_5",
    "type": "SP",
    "bookNumber": 7,
    "page": 5,
    "title_en": "There is a one limply octopus!",
    "title_kr": "흐느적흐느적 문어가 한 마리 있어요!",
    "titleClip_en": "",
    "titleClip_kr": "",
    "sentances": [
      {
        "kr": "흐느적흐느적 문어가 몇마리 일까?",
        "priority": 20,
        "clip_kr": "",
        "value": "How many limply octopuses are there?",
        "clip": "",
        "key": null,
        "en": "How many limply octopuses are there?",
        "clip_en": "",
        "words": [
          "How",
          "many",
          "limply",
          "octopuses",
          "are",
          "there?"
        ]
      },
      {
        "kr": "2-1 = 1",
        "priority": 21,
        "clip_kr": "",
        "value": "2 - 1 = 1",
        "clip": "",
        "key": null,
        "en": "2 - 1 = 1",
        "clip_en": "",
        "words": [
          "2",
          "-",
          "1",
          "=",
          "1"
        ]
      },
      {
        "kr": "",
        "priority": 22,
        "clip_kr": "",
        "value": "Two minus one equals one.",
        "clip": "",
        "key": null,
        "en": "Two minus one equals one.",
        "clip_en": "",
        "words": [
          "Two",
          "minus",
          "one",
          "equals",
          "one."
        ]
      }
    ],
    "conversations": [
      {
        "priority": 20,
        "speaker": "B",
        "value": "There are two limply octopuses.",
        "clip": ""
      },
      {
        "priority": 21,
        "speaker": "B",
        "value": "Then, shark eats one octopus.",
        "clip": ""
      },
      {
        "priority": 22,
        "speaker": "A",
        "value": "Okay.",
        "clip": ""
      },
      {
        "priority": 23,
        "speaker": "A",
        "value": "Then, we can make a simple formula.",
        "clip": ""
      }
    ],
    "words": [
      {
        "value": "crab",
        "extension": "jpg",
        "clip": ""
      },
      {
        "value": "lobsterclam",
        "extension": "jpg",
        "clip": ""
      },
      {
        "value": "octopus",
        "extension": "jpg",
        "clip": ""
      },
      {
        "value": "round fish",
        "extension": "jpg",
        "clip": ""
      },
      {
        "value": "sharp fish",
        "extension": "jpg",
        "clip": ""
      },
      {
        "value": "starfish",
        "extension": "jpg",
        "clip": ""
      }
    ]
  },
  {
    "key": "SP_7_6",
    "type": "SP",
    "bookNumber": 7,
    "page": 6,
    "title_en": "How many wiggling star fish are there?",
    "title_kr": "꾸물꾸물 불가사리가 몇마리 일까?",
    "titleClip_en": "",
    "titleClip_kr": "",
    "sentances": [
      {
        "kr": "흐느적흐느적 문어가 한 마리 있어요!",
        "priority": 24,
        "clip_kr": "",
        "value": "There is a one limply octopus!",
        "clip": "",
        "key": null,
        "en": "There is a one limply octopus!",
        "clip_en": "",
        "words": [
          "There",
          "is",
          "a",
          "one",
          "limply",
          "octopus!"
        ]
      }
    ],
    "conversations": [
      {
        "priority": 24,
        "speaker": "A",
        "value": "Two octopuses minus one octopus equals one octopus.",
        "clip": ""
      },
      {
        "priority": 25,
        "speaker": "A",
        "value": "Well. Can you tell me the answer of this formula?",
        "clip": ""
      },
      {
        "priority": 26,
        "speaker": "B",
        "value": "Yes, I can!",
        "clip": ""
      },
      {
        "priority": 27,
        "speaker": "B",
        "value": "The answer is one limply octopus.",
        "clip": ""
      },
      {
        "priority": 28,
        "speaker": "A",
        "value": "Good job!",
        "clip": ""
      }
    ],
    "words": [
      {
        "value": "crab",
        "extension": "jpg",
        "clip": ""
      },
      {
        "value": "lobsterclam",
        "extension": "jpg",
        "clip": ""
      },
      {
        "value": "octopus",
        "extension": "jpg",
        "clip": ""
      },
      {
        "value": "round fish",
        "extension": "jpg",
        "clip": ""
      },
      {
        "value": "sharp fish",
        "extension": "jpg",
        "clip": ""
      },
      {
        "value": "starfish",
        "extension": "jpg",
        "clip": ""
      }
    ]
  },
  {
    "key": "SP_7_7",
    "type": "SP",
    "bookNumber": 7,
    "page": 7,
    "title_en": "There are four wiggling star fish!",
    "title_kr": "꾸물꾸물 불가사리가 네 마리 있어요!",
    "titleClip_en": "",
    "titleClip_kr": "",
    "sentances": [
      {
        "kr": "꾸물꾸물 불가사리가 몇마리 일까?",
        "priority": 29,
        "clip_kr": "",
        "value": "How many wiggling star fish are there?",
        "clip": "",
        "key": null,
        "en": "How many wiggling star fish are there?",
        "clip_en": "",
        "words": [
          "How",
          "many",
          "wiggling",
          "star",
          "fish",
          "are",
          "there?"
        ]
      },
      {
        "kr": "2+2 = 4",
        "priority": 30,
        "clip_kr": "",
        "value": "2 + 2 = 4",
        "clip": "",
        "key": null,
        "en": "2 + 2 = 4",
        "clip_en": "",
        "words": [
          "2",
          "+",
          "2",
          "=",
          "4"
        ]
      },
      {
        "kr": "",
        "priority": 31,
        "clip_kr": "",
        "value": "Two and two is four.",
        "clip": "",
        "key": null,
        "en": "Two and two is four.",
        "clip_en": "",
        "words": [
          "Two",
          "and",
          "two",
          "is",
          "four."
        ]
      }
    ],
    "conversations": [
      {
        "priority": 29,
        "speaker": "B",
        "value": "There are two wiggling star fish!",
        "clip": ""
      },
      {
        "priority": 30,
        "speaker": "B",
        "value": "Then, two more wiggling star fish come.",
        "clip": ""
      },
      {
        "priority": 31,
        "speaker": "A",
        "value": "Well, we can make a simple formula.",
        "clip": ""
      },
      {
        "priority": 32,
        "speaker": "B",
        "value": "I can make it!",
        "clip": ""
      }
    ],
    "words": [
      {
        "value": "crab",
        "extension": "jpg",
        "clip": ""
      },
      {
        "value": "lobsterclam",
        "extension": "jpg",
        "clip": ""
      },
      {
        "value": "octopus",
        "extension": "jpg",
        "clip": ""
      },
      {
        "value": "round fish",
        "extension": "jpg",
        "clip": ""
      },
      {
        "value": "sharp fish",
        "extension": "jpg",
        "clip": ""
      },
      {
        "value": "starfish",
        "extension": "jpg",
        "clip": ""
      }
    ]
  },
  {
    "key": "SP_7_8",
    "type": "SP",
    "bookNumber": 7,
    "page": 8,
    "title_en": "How many waddling crabs are there?",
    "title_kr": "뒤뚱뒤뚱 꽃게가 몇마리 일까?",
    "titleClip_en": "",
    "titleClip_kr": "",
    "sentances": [
      {
        "kr": "꾸물꾸물 불가사리가 네 마리 있어요!",
        "priority": 33,
        "clip_kr": "",
        "value": "There are four wiggling star fish!",
        "clip": "",
        "key": null,
        "en": "There are four wiggling star fish!",
        "clip_en": "",
        "words": [
          "There",
          "are",
          "four",
          "wiggling",
          "star",
          "fish!"
        ]
      }
    ],
    "conversations": [
      {
        "priority": 33,
        "speaker": "B",
        "value": "Two star fish and two star fish is four star fish!",
        "clip": ""
      },
      {
        "priority": 34,
        "speaker": "A",
        "value": "Good answer!",
        "clip": ""
      },
      {
        "priority": 35,
        "speaker": "A",
        "value": "There are four star fish.",
        "clip": ""
      }
    ],
    "words": [
      {
        "value": "crab",
        "extension": "jpg",
        "clip": ""
      },
      {
        "value": "lobsterclam",
        "extension": "jpg",
        "clip": ""
      },
      {
        "value": "octopus",
        "extension": "jpg",
        "clip": ""
      },
      {
        "value": "round fish",
        "extension": "jpg",
        "clip": ""
      },
      {
        "value": "sharp fish",
        "extension": "jpg",
        "clip": ""
      },
      {
        "value": "starfish",
        "extension": "jpg",
        "clip": ""
      }
    ]
  },
  {
    "key": "SP_7_9",
    "type": "SP",
    "bookNumber": 7,
    "page": 9,
    "title_en": "There are three waddling crab!",
    "title_kr": "뒤뚱뒤뚱 꽃게가 세 마리 있어요!",
    "titleClip_en": "",
    "titleClip_kr": "",
    "sentances": [
      {
        "kr": "뒤뚱뒤뚱 꽃게가 몇마리 일까?",
        "priority": 36,
        "clip_kr": "",
        "value": "How many waddling crabs are there?",
        "clip": "",
        "key": null,
        "en": "How many waddling crabs are there?",
        "clip_en": "",
        "words": [
          "How",
          "many",
          "waddling",
          "crabs",
          "are",
          "there?"
        ]
      },
      {
        "kr": "2+1 = 3",
        "priority": 37,
        "clip_kr": "",
        "value": "2 + 1 = 3",
        "clip": "",
        "key": null,
        "en": "2 + 1 = 3",
        "clip_en": "",
        "words": [
          "2",
          "+",
          "1",
          "=",
          "3"
        ]
      },
      {
        "kr": "",
        "priority": 38,
        "clip_kr": "",
        "value": "Two and one is three.",
        "clip": "",
        "key": null,
        "en": "Two and one is three.",
        "clip_en": "",
        "words": [
          "Two",
          "and",
          "one",
          "is",
          "three."
        ]
      }
    ],
    "conversations": [
      {
        "priority": 36,
        "speaker": "B",
        "value": "There are two waddling crabs.",
        "clip": ""
      },
      {
        "priority": 37,
        "speaker": "B",
        "value": "Then, one more waddling crab comes.",
        "clip": ""
      },
      {
        "priority": 38,
        "speaker": "A",
        "value": "Can you make a simple formula?",
        "clip": ""
      },
      {
        "priority": 39,
        "speaker": "B",
        "value": "I can make it!",
        "clip": ""
      }
    ],
    "words": [
      {
        "value": "crab",
        "extension": "jpg",
        "clip": ""
      },
      {
        "value": "lobsterclam",
        "extension": "jpg",
        "clip": ""
      },
      {
        "value": "octopus",
        "extension": "jpg",
        "clip": ""
      },
      {
        "value": "round fish",
        "extension": "jpg",
        "clip": ""
      },
      {
        "value": "sharp fish",
        "extension": "jpg",
        "clip": ""
      },
      {
        "value": "starfish",
        "extension": "jpg",
        "clip": ""
      }
    ]
  },
  {
    "key": "SP_7_10",
    "type": "SP",
    "bookNumber": 7,
    "page": 10,
    "title_en": "How many crackling lobsters are there?",
    "title_kr": "따각따각 바닷가재가 몇마리 일까?",
    "titleClip_en": "",
    "titleClip_kr": "",
    "sentances": [
      {
        "kr": "뒤뚱뒤뚱 꽃게가 세 마리 있어요!",
        "priority": 40,
        "clip_kr": "",
        "value": "There are three waddling crab!",
        "clip": "",
        "key": null,
        "en": "There are three waddling crab!",
        "clip_en": "",
        "words": [
          "There",
          "are",
          "three",
          "waddling",
          "crab!"
        ]
      }
    ],
    "conversations": [
      {
        "priority": 40,
        "speaker": "B",
        "value": "Two crabs and one crab is three crabs.",
        "clip": ""
      },
      {
        "priority": 41,
        "speaker": "A",
        "value": "Great answer!",
        "clip": ""
      },
      {
        "priority": 42,
        "speaker": "A",
        "value": "There are three crabs.",
        "clip": ""
      }
    ],
    "words": [
      {
        "value": "crab",
        "extension": "jpg",
        "clip": ""
      },
      {
        "value": "lobsterclam",
        "extension": "jpg",
        "clip": ""
      },
      {
        "value": "octopus",
        "extension": "jpg",
        "clip": ""
      },
      {
        "value": "round fish",
        "extension": "jpg",
        "clip": ""
      },
      {
        "value": "sharp fish",
        "extension": "jpg",
        "clip": ""
      },
      {
        "value": "starfish",
        "extension": "jpg",
        "clip": ""
      }
    ]
  },
  {
    "key": "SP_7_11",
    "type": "SP",
    "bookNumber": 7,
    "page": 11,
    "title_en": "There are four crackling lobster!",
    "title_kr": "따각따각 바닷가재가 네 마리 있어요!",
    "titleClip_en": "",
    "titleClip_kr": "",
    "sentances": [
      {
        "kr": "따각따각 바닷가재가 몇마리 일까?",
        "priority": 43,
        "clip_kr": "",
        "value": "How many crackling lobsters are there?",
        "clip": "",
        "key": null,
        "en": "How many crackling lobsters are there?",
        "clip_en": "",
        "words": [
          "How",
          "many",
          "crackling",
          "lobsters",
          "are",
          "there?"
        ]
      },
      {
        "kr": "3+1 = 4",
        "priority": 44,
        "clip_kr": "",
        "value": "3 + 1 = 4",
        "clip": "",
        "key": null,
        "en": "3 + 1 = 4",
        "clip_en": "",
        "words": [
          "3",
          "+",
          "1",
          "=",
          "4"
        ]
      },
      {
        "kr": "",
        "priority": 45,
        "clip_kr": "",
        "value": "Three and one is four.",
        "clip": "",
        "key": null,
        "en": "Three and one is four.",
        "clip_en": "",
        "words": [
          "Three",
          "and",
          "one",
          "is",
          "four."
        ]
      }
    ],
    "conversations": [
      {
        "priority": 43,
        "speaker": "B",
        "value": "There are three crackling lobsters.",
        "clip": ""
      },
      {
        "priority": 44,
        "speaker": "B",
        "value": "Then, one more crackling lobster comes.",
        "clip": ""
      },
      {
        "priority": 45,
        "speaker": "A",
        "value": "Can you make a simple formula?",
        "clip": ""
      },
      {
        "priority": 46,
        "speaker": "B",
        "value": "Yes, I can!",
        "clip": ""
      }
    ],
    "words": [
      {
        "value": "crab",
        "extension": "jpg",
        "clip": ""
      },
      {
        "value": "lobsterclam",
        "extension": "jpg",
        "clip": ""
      },
      {
        "value": "octopus",
        "extension": "jpg",
        "clip": ""
      },
      {
        "value": "round fish",
        "extension": "jpg",
        "clip": ""
      },
      {
        "value": "sharp fish",
        "extension": "jpg",
        "clip": ""
      },
      {
        "value": "starfish",
        "extension": "jpg",
        "clip": ""
      }
    ]
  },
  {
    "key": "SP_7_12",
    "type": "SP",
    "bookNumber": 7,
    "page": 12,
    "title_en": "How many rolling clams are there?",
    "title_kr": "데굴데굴 조개가 몇마리 일까?",
    "titleClip_en": "",
    "titleClip_kr": "",
    "sentances": [
      {
        "kr": "따각따각 바닷가재가 네 마리 있어요!",
        "priority": 47,
        "clip_kr": "",
        "value": "There are four crackling lobster!",
        "clip": "",
        "key": null,
        "en": "There are four crackling lobster!",
        "clip_en": "",
        "words": [
          "There",
          "are",
          "four",
          "crackling",
          "lobster!"
        ]
      }
    ],
    "conversations": [
      {
        "priority": 47,
        "speaker": "B",
        "value": "Three lobsters and one lobster is four lobsters.",
        "clip": ""
      },
      {
        "priority": 48,
        "speaker": "A",
        "value": "Good job!",
        "clip": ""
      },
      {
        "priority": 49,
        "speaker": "A",
        "value": "There are four crackling lobsters.",
        "clip": ""
      }
    ],
    "words": [
      {
        "value": "crab",
        "extension": "jpg",
        "clip": ""
      },
      {
        "value": "lobsterclam",
        "extension": "jpg",
        "clip": ""
      },
      {
        "value": "octopus",
        "extension": "jpg",
        "clip": ""
      },
      {
        "value": "round fish",
        "extension": "jpg",
        "clip": ""
      },
      {
        "value": "sharp fish",
        "extension": "jpg",
        "clip": ""
      },
      {
        "value": "starfish",
        "extension": "jpg",
        "clip": ""
      }
    ]
  },
  {
    "key": "SP_7_13",
    "type": "SP",
    "bookNumber": 7,
    "page": 13,
    "title_en": "There are three rolling clam!",
    "title_kr": "데굴데굴 조개가 세 마리 있어요!",
    "titleClip_en": "",
    "titleClip_kr": "",
    "sentances": [
      {
        "kr": "데굴데굴 조개가 몇마리 일까?",
        "priority": 50,
        "clip_kr": "",
        "value": "How many rolling clams are there?",
        "clip": "",
        "key": null,
        "en": "How many rolling clams are there?",
        "clip_en": "",
        "words": [
          "How",
          "many",
          "rolling",
          "clams",
          "are",
          "there?"
        ]
      },
      {
        "kr": "5-2 = 3",
        "priority": 51,
        "clip_kr": "",
        "value": "5 - 2 = 3",
        "clip": "",
        "key": null,
        "en": "5 - 2 = 3",
        "clip_en": "",
        "words": [
          "5",
          "-",
          "2",
          "=",
          "3"
        ]
      },
      {
        "kr": "",
        "priority": 52,
        "clip_kr": "",
        "value": "Five minus two equals three.",
        "clip": "",
        "key": null,
        "en": "Five minus two equals three.",
        "clip_en": "",
        "words": [
          "Five",
          "minus",
          "two",
          "equals",
          "three."
        ]
      }
    ],
    "conversations": [
      {
        "priority": 50,
        "speaker": "A",
        "value": "Last question!",
        "clip": ""
      },
      {
        "priority": 51,
        "speaker": "A",
        "value": "How many rolling clams are there?",
        "clip": ""
      },
      {
        "priority": 52,
        "speaker": "B",
        "value": "Well, there are five rolling clams.",
        "clip": ""
      },
      {
        "priority": 53,
        "speaker": "B",
        "value": "Then, shark eats two rolling clams.",
        "clip": ""
      }
    ],
    "words": [
      {
        "value": "crab",
        "extension": "jpg",
        "clip": ""
      },
      {
        "value": "lobsterclam",
        "extension": "jpg",
        "clip": ""
      },
      {
        "value": "octopus",
        "extension": "jpg",
        "clip": ""
      },
      {
        "value": "round fish",
        "extension": "jpg",
        "clip": ""
      },
      {
        "value": "sharp fish",
        "extension": "jpg",
        "clip": ""
      },
      {
        "value": "starfish",
        "extension": "jpg",
        "clip": ""
      }
    ]
  },
  {
    "key": "SP_7_14",
    "type": "SP",
    "bookNumber": 7,
    "page": 14,
    "title_en": "",
    "title_kr": "",
    "titleClip_en": "",
    "titleClip_kr": "",
    "sentances": [
      {
        "kr": "데굴데굴 조개가 세 마리 있어요!",
        "priority": 54,
        "clip_kr": "",
        "value": "There are three rolling clam!",
        "clip": "",
        "key": null,
        "en": "There are three rolling clam!",
        "clip_en": "",
        "words": [
          "There",
          "are",
          "three",
          "rolling",
          "clam!"
        ]
      }
    ],
    "conversations": [
      {
        "priority": 54,
        "speaker": "A",
        "value": "Can you make a simple formula?",
        "clip": ""
      },
      {
        "priority": 55,
        "speaker": "B",
        "value": "Yes, I can!",
        "clip": ""
      },
      {
        "priority": 56,
        "speaker": "B",
        "value": "Five clams minus two clams equals three clams!",
        "clip": ""
      },
      {
        "priority": 57,
        "speaker": "A",
        "value": "You're right!",
        "clip": ""
      },
      {
        "priority": 58,
        "speaker": "A",
        "value": "Now, are you good at math?!",
        "clip": ""
      },
      {
        "priority": 59,
        "speaker": "B",
        "value": "Yes, I am!",
        "clip": ""
      },
      {
        "priority": 60,
        "speaker": "B",
        "value": "Thanks for you!",
        "clip": ""
      }
    ],
    "words": [
      {
        "value": "crab",
        "extension": "jpg",
        "clip": ""
      },
      {
        "value": "lobsterclam",
        "extension": "jpg",
        "clip": ""
      },
      {
        "value": "octopus",
        "extension": "jpg",
        "clip": ""
      },
      {
        "value": "round fish",
        "extension": "jpg",
        "clip": ""
      },
      {
        "value": "sharp fish",
        "extension": "jpg",
        "clip": ""
      },
      {
        "value": "starfish",
        "extension": "jpg",
        "clip": ""
      }
    ]
  }
]